{
  "node": {
    "70330047c1298307ff7fdef5110df01c092421e5b3": {
      "workers": {
        "app/dashboard/page": {
          "moduleId": 59276,
          "async": false,
          "exportedName": "generateAndSaveArticleAction",
          "filename": "app/actions.ts"
        }
      },
      "layer": {
        "app/dashboard/page": "action-browser"
      },
      "exportedName": "generateAndSaveArticleAction",
      "filename": "app/actions.ts"
    },
    "00d002ddfe012e24faec6cada1f9d9a8ced2f790f6": {
      "workers": {
        "app/dashboard/page": {
          "moduleId": 59276,
          "async": false,
          "exportedName": "getArticlesAction",
          "filename": "app/actions.ts"
        }
      },
      "layer": {
        "app/dashboard/page": "action-browser"
      },
      "exportedName": "getArticlesAction",
      "filename": "app/actions.ts"
    }
  },
  "edge": {}
}